odoo/addons/web_disable_browser_autocomplete/README.rst
odoo/addons/web_disable_browser_autocomplete/__init__.py
odoo/addons/web_disable_browser_autocomplete/__manifest__.py
odoo/addons/web_disable_browser_autocomplete/i18n/ca.po
odoo/addons/web_disable_browser_autocomplete/i18n/de.po
odoo/addons/web_disable_browser_autocomplete/i18n/es.po
odoo/addons/web_disable_browser_autocomplete/i18n/fr.po
odoo/addons/web_disable_browser_autocomplete/i18n/pt_BR.po
odoo/addons/web_disable_browser_autocomplete/i18n/tr.po
odoo/addons/web_disable_browser_autocomplete/i18n/web_disable_browser_autocomplete.pot
odoo/addons/web_disable_browser_autocomplete/readme/CONFIGURE.rst
odoo/addons/web_disable_browser_autocomplete/readme/CONTRIBUTORS.rst
odoo/addons/web_disable_browser_autocomplete/readme/DESCRIPTION.rst
odoo/addons/web_disable_browser_autocomplete/readme/INSTALL.rst
odoo/addons/web_disable_browser_autocomplete/readme/ROADMAP.rst
odoo/addons/web_disable_browser_autocomplete/readme/USAGE.rst
odoo/addons/web_disable_browser_autocomplete/static/description/icon.png
odoo/addons/web_disable_browser_autocomplete/static/description/index.html
odoo/addons/web_disable_browser_autocomplete/static/src/xml/base.xml
odoo12_addon_web_disable_browser_autocomplete-12.0.1.0.2.dist-info/METADATA
odoo12_addon_web_disable_browser_autocomplete-12.0.1.0.2.dist-info/WHEEL
odoo12_addon_web_disable_browser_autocomplete-12.0.1.0.2.dist-info/top_level.txt
odoo12_addon_web_disable_browser_autocomplete-12.0.1.0.2.dist-info/RECORD
